LICENSE
redis_index/__init__.py
redis_index/redis_index.py
redis_index-0.8.0.dist-info/LICENSE
redis_index-0.8.0.dist-info/METADATA
redis_index-0.8.0.dist-info/WHEEL
redis_index-0.8.0.dist-info/RECORD
