Metadata-Version: 2.1
Name: redis-index
Version: 0.8.0
Summary: Inverted Index using efficient Redis set
Home-page: https://github.com/ErhoSen/redis-index
License: MIT
Keywords: redis,index,gin,intersection,filters
Author: Vladimir Vyazovetskov
Author-email: erhosen@gmail.com
Requires-Python: >=3.8,<4.0
Classifier: Development Status :: 3 - Alpha
Classifier: Environment :: Other Environment
Classifier: Intended Audience :: Developers
Classifier: License :: OSI Approved :: MIT License
Classifier: Operating System :: OS Independent
Classifier: Programming Language :: Python :: 3
Classifier: Programming Language :: Python :: 3.8
Classifier: Programming Language :: Python :: 3.9
Classifier: Programming Language :: Python :: 3.10
Classifier: Programming Language :: Python :: 3.11
Classifier: Programming Language :: Python :: 3.12
Classifier: Topic :: Software Development :: Libraries :: Python Modules
Classifier: Typing :: Typed
Requires-Dist: hot_redis (>=0.3.0,<0.4.0)
Requires-Dist: inflection (>=0.3.1,<0.4.0)
Requires-Dist: redis (<=4.4.4)
Requires-Dist: statsd (>=3.3,<4.0)
Project-URL: Repository, https://github.com/ErhoSen/redis-index
